{
    "index": {
        "method": "GET",
        "mounts": [
            {
                "name": "index.html",
                "mediaType": "text/html",
                "stage": "output"
            },
            {
                "name": "deploy-index.html",
                "mediaType": "text/html",
                "stage": "deployment"
            },
            {
                "name": "index.js",
                "mediaType": "text/javascript",
                "stage": "deployment"
            }
        ]
    },
    "next_frame": {
        "method": "GET",
        "mounts": [
            {
                "name": "snake_game.jpeg",
                "mediaType": "image/jpeg",
                "stage": "output"
            }
        ]
    }
}
